microspec-0.1.1a9.data/data/share/microspeclib/cfg/microspec.json
microspec-0.1.1a9.data/data/share/microspeclib/doc/build/html/bin.html
microspec-0.1.1a9.data/data/share/microspeclib/doc/build/html/bin.microspec_cmdline.html
microspec-0.1.1a9.data/data/share/microspeclib/doc/build/html/bin.microspec_emulator.html
microspec-0.1.1a9.data/data/share/microspeclib/doc/build/html/bin.microspec_expert_example.html
microspec-0.1.1a9.data/data/share/microspeclib/doc/build/html/bin.microspec_simple_example.html
microspec-0.1.1a9.data/data/share/microspeclib/doc/build/html/cfg.html
microspec-0.1.1a9.data/data/share/microspeclib/doc/build/html/cfg.microspec.html
microspec-0.1.1a9.data/data/share/microspeclib/doc/build/html/dev-kit-API-guide.html
microspec-0.1.1a9.data/data/share/microspeclib/doc/build/html/genindex.html
microspec-0.1.1a9.data/data/share/microspeclib/doc/build/html/getting-started.html
microspec-0.1.1a9.data/data/share/microspeclib/doc/build/html/how-to-handle-timeouts.html
microspec-0.1.1a9.data/data/share/microspeclib/doc/build/html/how-to-read-this-documentation.html
microspec-0.1.1a9.data/data/share/microspeclib/doc/build/html/index.html
microspec-0.1.1a9.data/data/share/microspeclib/doc/build/html/microspec-dev.html
microspec-0.1.1a9.data/data/share/microspeclib/doc/build/html/microspeclib.cmdline.html
microspec-0.1.1a9.data/data/share/microspeclib/doc/build/html/microspeclib.datatypes.bridge.html
microspec-0.1.1a9.data/data/share/microspeclib/doc/build/html/microspeclib.datatypes.command.html
microspec-0.1.1a9.data/data/share/microspeclib/doc/build/html/microspeclib.datatypes.html
microspec-0.1.1a9.data/data/share/microspeclib/doc/build/html/microspeclib.datatypes.sensor.html
microspec-0.1.1a9.data/data/share/microspeclib/doc/build/html/microspeclib.datatypes.types.html
microspec-0.1.1a9.data/data/share/microspeclib/doc/build/html/microspeclib.exceptions.html
microspec-0.1.1a9.data/data/share/microspeclib/doc/build/html/microspeclib.expert.html
microspec-0.1.1a9.dist-info/LICENSE.md
microspec-0.1.1a9.dist-info/METADATA
microspec-0.1.1a9.dist-info/WHEEL
microspec-0.1.1a9.dist-info/entry_points.txt
microspec-0.1.1a9.dist-info/top_level.txt
microspec-0.1.1a9.dist-info/RECORD
