Metadata-Version: 2.1
Name: microspec
Version: 0.1.1a9
Summary: Python API for the Chromation spectrometer dev-kit
Home-page: https://github.com/microspectrometer/microspec
Author: Chromation
Author-email: mike@chromationspec.com
License: MIT
Project-URL: Chromation, https://www.chromation.com/
Project-URL: Thanks To, http://eruciform.com/
Keywords: spectrometer API USB serial hardware embedded-systems
Platform: Windows
Platform: Mac
Platform: Linux
Classifier: Development Status :: 3 - Alpha
Classifier: Intended Audience :: Developers
Classifier: License :: OSI Approved :: MIT License
Classifier: Programming Language :: Python :: 3
Classifier: Programming Language :: Python :: 3.7
Classifier: Programming Language :: Python :: 3.8
Classifier: Topic :: Scientific/Engineering
Classifier: Topic :: Software Development :: Embedded Systems
Classifier: Topic :: Terminals :: Serial
Requires-Python: >=3.7
Requires-Dist: pyserial
Provides-Extra: dev
Requires-Dist: sphinx ; extra == 'dev'
Requires-Dist: sphinx-rtd-theme ; extra == 'dev'
Requires-Dist: recommonmark ; extra == 'dev'
Requires-Dist: m2r ; extra == 'dev'
Requires-Dist: sphinxcontrib-argdoc ; extra == 'dev'
Requires-Dist: pytest ; extra == 'dev'
Requires-Dist: pytest-testdox ; extra == 'dev'
Requires-Dist: tabulate ; extra == 'dev'
Requires-Dist: psutil ; extra == 'dev'
